<?xml version="1.0" encoding="utf-8"?>
<!DOCTYPE hibernate-mapping PUBLIC 
 "-//Hibernate/Hibernate Mapping DTD//EN"
 "http://www.hibernate.org/dtd/hibernate-mapping-3.0.dtd"> 

<hibernate-mapping>
   <class name="com.managetransfer.businessobject.TermLetterCustomer" table="mttermletter">
      <meta attribute="class-description">
         This class contains the  term letter customer
      </meta>
       
	  <id name="objectId" type="string" column="r_object_id" length="16">
      </id>
      
      <property name="objectName" column="object_name" type="string"/>
      <property name="folderPath" column="folder_path" type="string"/>
      <property name="ownerName" column="owner_name" type="string"/>
      <property name="aclName" column="acl_name" type="string"/>
      
       <property name="docCategory" column="doc_category" type="string"/>   
       <property name="docDate" column="doc_date" type="timestamp"  /> 
       <property name="refNum" column="ref_num" type="int"  />       
       <property name="isActive" column="is_active" type="boolean"  />        
              
	   <property name="mtSequenceName" column="mt_sequence_name" type="string" length="16"/>
      <property name="mtSequenceNumber" column="mt_sequence_number" type="int" />
      <property name="mtCreateDate" column="mt_create_date" type="timestamp"  />
      <property name="mtModifyDate" column="mt_modify_date" type="timestamp"  />
      <property name="mtErrorDesc"  column="mt_error_description" type="string" length="255"/>
      <property name="mtStatus"  column="mt_status" type="string" length="10"/>
      <property name="mtProcessId" column="mt_process_id" type="int" />
      <property name="mtRepositoryPath" column="mt_repo_path" type="string" length="255"/>
   </class>
</hibernate-mapping>